LICENSE.rst
haapi/games/rawg/__init__.py
haapi/games/rawg/async_api.py
haapi/games/rawg/constants.py
haapi/games/rawg/objects/__init__.py
haapi/games/rawg/objects/game.py
haapi/games/rawg/objects/genre.py
haapi/games/rawg/py.typed
haapi.games.rawg-0.2.0.dist-info/LICENSE.rst
haapi.games.rawg-0.2.0.dist-info/WHEEL
haapi.games.rawg-0.2.0.dist-info/METADATA
haapi.games.rawg-0.2.0.dist-info/RECORD
