Metadata-Version: 2.1
Name: haapi.games.rawg
Version: 0.2.0
Summary: Haapi Games Rawg
Home-page: https://github.com/Haapi-Games/haapi.games.rawg
License: MIT
Author: Haapi
Author-email: haapigeek@gmail.com
Requires-Python: >=3.6.1,<4.0.0
Classifier: License :: OSI Approved :: MIT License
Classifier: Programming Language :: Python :: 3
Classifier: Programming Language :: Python :: 3.6
Classifier: Programming Language :: Python :: 3.7
Classifier: Programming Language :: Python :: 3.8
Classifier: Programming Language :: Python :: 3.9
Requires-Dist: aiohttp[speedups] (>=3.7.3,<4.0.0)
Requires-Dist: desert (>=2020.11.18,<2021.0.0)
Project-URL: Changelog, https://github.com/Haapi-Games/haapi.games.rawg/releases
Project-URL: Documentation, https://haapigamesrawg.readthedocs.io
Project-URL: Repository, https://github.com/Haapi-Games/haapi.games.rawg
